pvresqml/__about__.py
pvresqml/__init__.py
pvresqml/_common.py
pvresqml/_read.py
pvresqml/_save.py
pvresqml/examples/__init__.py
pvresqml/examples/examples.py
pyvista_resqml-0.1.0.dist-info/licenses/LICENSE
pyvista_resqml-0.1.0.dist-info/METADATA
pyvista_resqml-0.1.0.dist-info/WHEEL
pyvista_resqml-0.1.0.dist-info/top_level.txt
pyvista_resqml-0.1.0.dist-info/RECORD
