Metadata-Version: 2.4
Name: pyvista-resqml
Version: 0.1.0
Summary: RESQML extension for PyVista
Author-email: Keurfon Luu <kluu@intera.com>
License-Expression: BSD-3-Clause
Project-URL: Homepage, https://github.com/INTERA-Inc/pyvista-resqml
Project-URL: Code, https://github.com/INTERA-Inc/pyvista-resqml
Project-URL: Issues, https://github.com/INTERA-Inc/pyvista-resqml/issues
Keywords: geological modeling,pyvista,resqml,epc
Classifier: Operating System :: OS Independent
Classifier: Development Status :: 4 - Beta
Classifier: Programming Language :: Python :: 3.9
Classifier: Programming Language :: Python :: 3.10
Classifier: Programming Language :: Python :: 3.11
Classifier: Programming Language :: Python :: 3.12
Classifier: Natural Language :: English
Classifier: Intended Audience :: Science/Research
Classifier: Topic :: Scientific/Engineering
Requires-Python: <3.13,>=3.9
License-File: LICENSE
Requires-Dist: numpy>=1.13.0
Requires-Dist: pyvista-gridder>=0.5.3
Requires-Dist: resqpy>=5.0
Dynamic: license-file
